discord_mcp_server/__init__.py
discord_mcp_server/cli.py
discord_mcp_server/server.py
discord_mcp_server/tools.py
datagen_discord_mcp_server-1.0.1.dist-info/METADATA
datagen_discord_mcp_server-1.0.1.dist-info/WHEEL
datagen_discord_mcp_server-1.0.1.dist-info/entry_points.txt
datagen_discord_mcp_server-1.0.1.dist-info/licenses/LICENSE
datagen_discord_mcp_server-1.0.1.dist-info/RECORD
