Metadata-Version: 2.4
Name: datagen-discord-mcp-server
Version: 1.0.1
Summary: A Model Context Protocol server for Discord integration
Project-URL: Homepage, https://github.com/yourusername/discord-mcp-server
Project-URL: Repository, https://github.com/yourusername/discord-mcp-server.git
Project-URL: Documentation, https://github.com/yourusername/discord-mcp-server#readme
Project-URL: Bug Tracker, https://github.com/yourusername/discord-mcp-server/issues
Author-email: Your Name <your.email@example.com>
License: MIT
License-File: LICENSE
Keywords: ai,claude,discord,mcp,model-context-protocol
Classifier: Development Status :: 4 - Beta
Classifier: Intended Audience :: Developers
Classifier: License :: OSI Approved :: MIT License
Classifier: Operating System :: OS Independent
Classifier: Programming Language :: Python :: 3
Classifier: Programming Language :: Python :: 3 :: Only
Classifier: Programming Language :: Python :: 3.8
Classifier: Programming Language :: Python :: 3.9
Classifier: Programming Language :: Python :: 3.10
Classifier: Programming Language :: Python :: 3.11
Classifier: Programming Language :: Python :: 3.12
Classifier: Topic :: Communications :: Chat
Classifier: Topic :: Software Development :: Libraries :: Python Modules
Requires-Python: <3.13,>=3.8
Requires-Dist: discord-py>=2.3.2
Requires-Dist: mcp>=1.0.0
Requires-Dist: python-dotenv>=1.0.0
Provides-Extra: dev
Requires-Dist: black>=23.0.0; extra == 'dev'
Requires-Dist: build>=0.10.0; extra == 'dev'
Requires-Dist: isort>=5.12.0; extra == 'dev'
Requires-Dist: mypy>=1.0.0; extra == 'dev'
Requires-Dist: pytest-asyncio>=0.21.0; extra == 'dev'
Requires-Dist: pytest>=7.0.0; extra == 'dev'
Requires-Dist: twine>=4.0.0; extra == 'dev'
